asdf_zarr/__init__.py
asdf_zarr/_version.py
asdf_zarr/converter.py
asdf_zarr/extensions.py
asdf_zarr/storage.py
asdf_zarr/util.py
asdf_zarr/tests/__init__.py
asdf_zarr/tests/test_zarr.py
asdf_zarr-0.0.4.dist-info/LICENSE
asdf_zarr-0.0.4.dist-info/METADATA
asdf_zarr-0.0.4.dist-info/WHEEL
asdf_zarr-0.0.4.dist-info/entry_points.txt
asdf_zarr-0.0.4.dist-info/top_level.txt
asdf_zarr-0.0.4.dist-info/RECORD
