Metadata-Version: 2.1
Name: asdf_zarr
Version: 0.0.4
Summary: Asdf extension to support Zarr arrays
Author-email: The ASDF Developers <help@stsci.edu>
License: BSD 3-Clause License
Project-URL: documentation, https://asdf-zarr.readthedocs.io/en/latest
Project-URL: repository, https://github.com/asdf-format/asdf-zarr
Project-URL: tracker, https://github.com/asdf-format/asdf-zarr/issues
Classifier: Development Status :: 5 - Production/Stable
Classifier: License :: OSI Approved :: BSD License
Classifier: Programming Language :: Python
Classifier: Programming Language :: Python :: 3
Classifier: Programming Language :: Python :: 3.9
Classifier: Programming Language :: Python :: 3.10
Classifier: Programming Language :: Python :: 3.11
Classifier: Programming Language :: Python :: 3.12
Requires-Python: >=3.9
License-File: LICENSE
Requires-Dist: asdf >=3.0.0
Requires-Dist: zarr <3.0.0,>=2.14
Requires-Dist: fsspec
Provides-Extra: tests
Requires-Dist: pytest >=6 ; extra == 'tests'
